funapi/__init__.py
funmeta-0.0.1.dist-info/LICENSE
funmeta-0.0.1.dist-info/METADATA
funmeta-0.0.1.dist-info/WHEEL
funmeta-0.0.1.dist-info/entry_points.txt
funmeta-0.0.1.dist-info/top_level.txt
funmeta-0.0.1.dist-info/RECORD
